{
    "openapi":  "3.1.0",
    "info":  {
                 "title":  "Task Management Service",
                 "version":  "1.0.0"
             },
    "paths":  {
                  "/":  {
                            "get":  {
                                        "summary":  "Root",
                                        "operationId":  "root__get",
                                        "responses":  {
                                                          "200":  {
                                                                      "description":  "Successful Response",
                                                                      "content":  {
                                                                                      "application/json":  {
                                                                                                               "schema":  {

                                                                                                                          }
                                                                                                           }
                                                                                  }
                                                                  }
                                                      }
                                    }
                        },
                  "/health":  {
                                  "get":  {
                                              "summary":  "Health",
                                              "operationId":  "health_health_get",
                                              "responses":  {
                                                                "200":  {
                                                                            "description":  "Successful Response",
                                                                            "content":  {
                                                                                            "application/json":  {
                                                                                                                     "schema":  {

                                                                                                                                }
                                                                                                                 }
                                                                                        }
                                                                        }
                                                            }
                                          }
                              },
                  "/api/tasks/{uid}":  {
                                           "get":  {
                                                       "summary":  "Get Tasks",
                                                       "operationId":  "get_tasks_api_tasks__uid__get",
                                                       "parameters":  [
                                                                          {
                                                                              "name":  "uid",
                                                                              "in":  "path",
                                                                              "required":  true,
                                                                              "schema":  {
                                                                                             "type":  "string",
                                                                                             "title":  "Uid"
                                                                                         }
                                                                          }
                                                                      ],
                                                       "responses":  {
                                                                         "200":  {
                                                                                     "description":  "Successful Response",
                                                                                     "content":  {
                                                                                                     "application/json":  {
                                                                                                                              "schema":  {

                                                                                                                                         }
                                                                                                                          }
                                                                                                 }
                                                                                 },
                                                                         "422":  {
                                                                                     "description":  "Validation Error",
                                                                                     "content":  {
                                                                                                     "application/json":  {
                                                                                                                              "schema":  {
                                                                                                                                             "$ref":  "#/components/schemas/HTTPValidationError"
                                                                                                                                         }
                                                                                                                          }
                                                                                                 }
                                                                                 }
                                                                     }
                                                   }
                                       },
                  "/api/tasks/{uid}/complete":  {
                                                    "post":  {
                                                                 "summary":  "Complete Task",
                                                                 "operationId":  "complete_task_api_tasks__uid__complete_post",
                                                                 "parameters":  [
                                                                                    {
                                                                                        "name":  "uid",
                                                                                        "in":  "path",
                                                                                        "required":  true,
                                                                                        "schema":  {
                                                                                                       "type":  "string",
                                                                                                       "title":  "Uid"
                                                                                                   }
                                                                                    }
                                                                                ],
                                                                 "requestBody":  {
                                                                                     "required":  true,
                                                                                     "content":  {
                                                                                                     "application/json":  {
                                                                                                                              "schema":  {
                                                                                                                                             "type":  "object",
                                                                                                                                             "additionalProperties":  true,
                                                                                                                                             "title":  "Task Data"
                                                                                                                                         }
                                                                                                                          }
                                                                                                 }
                                                                                 },
                                                                 "responses":  {
                                                                                   "200":  {
                                                                                               "description":  "Successful Response",
                                                                                               "content":  {
                                                                                                               "application/json":  {
                                                                                                                                        "schema":  {

                                                                                                                                                   }
                                                                                                                                    }
                                                                                                           }
                                                                                           },
                                                                                   "422":  {
                                                                                               "description":  "Validation Error",
                                                                                               "content":  {
                                                                                                               "application/json":  {
                                                                                                                                        "schema":  {
                                                                                                                                                       "$ref":  "#/components/schemas/HTTPValidationError"
                                                                                                                                                   }
                                                                                                                                    }
                                                                                                           }
                                                                                           }
                                                                               }
                                                             }
                                                }
              },
    "components":  {
                       "schemas":  {
                                       "HTTPValidationError":  {
                                                                   "properties":  {
                                                                                      "detail":  {
                                                                                                     "items":  {
                                                                                                                   "$ref":  "#/components/schemas/ValidationError"
                                                                                                               },
                                                                                                     "type":  "array",
                                                                                                     "title":  "Detail"
                                                                                                 }
                                                                                  },
                                                                   "type":  "object",
                                                                   "title":  "HTTPValidationError"
                                                               },
                                       "ValidationError":  {
                                                               "properties":  {
                                                                                  "loc":  {
                                                                                              "items":  {
                                                                                                            "anyOf":  [
                                                                                                                          {
                                                                                                                              "type":  "string"
                                                                                                                          },
                                                                                                                          {
                                                                                                                              "type":  "integer"
                                                                                                                          }
                                                                                                                      ]
                                                                                                        },
                                                                                              "type":  "array",
                                                                                              "title":  "Location"
                                                                                          },
                                                                                  "msg":  {
                                                                                              "type":  "string",
                                                                                              "title":  "Message"
                                                                                          },
                                                                                  "type":  {
                                                                                               "type":  "string",
                                                                                               "title":  "Error Type"
                                                                                           }
                                                                              },
                                                               "type":  "object",
                                                               "required":  [
                                                                                "loc",
                                                                                "msg",
                                                                                "type"
                                                                            ],
                                                               "title":  "ValidationError"
                                                           }
                                   }
                   }
}
